hrtem_filter/__ini__.py
hrtem_filter/filters.py
hrtem_filter-0.0.1.post2.dist-info/METADATA
hrtem_filter-0.0.1.post2.dist-info/WHEEL
hrtem_filter-0.0.1.post2.dist-info/licenses/LICENSE
hrtem_filter-0.0.1.post2.dist-info/RECORD
