Metadata-Version: 2.1
Name: hrtem_filter
Version: 0.0.1.post2
Summary: Functions to filter HR(S)TEM images
Project-URL: Homepage, https://github.com/matao1984/hrtem_filter
Project-URL: Issues, https://github.com/matao1984/hrtem_filter/issues
Author-email: Tao Ma <matao1984@gmail.com>
License-File: LICENSE
Classifier: License :: OSI Approved :: MIT License
Classifier: Operating System :: OS Independent
Classifier: Programming Language :: Python :: 3
Requires-Python: >=3.8
Requires-Dist: numpy
Requires-Dist: pandas
Requires-Dist: scipy
